docs/changelog.rst
docs/conf.py
docs/configuration.rst
docs/contributing.rst
docs/definitions.py
docs/examples.rst
docs/index.rst
docs/installation.rst
docs/macros.rst
docs/usage.rst
sphinxcontrib/auto-render.min.js
sphinxcontrib/katex-math.css
sphinxcontrib/katex-server.js
sphinxcontrib/katex.min.js
sphinxcontrib/katex.py
sphinxcontrib_katex-0.9.11.dist-info/licenses/LICENSE
tests/test_katex_server.py
sphinxcontrib_katex-0.9.11.dist-info/METADATA
sphinxcontrib_katex-0.9.11.dist-info/WHEEL
sphinxcontrib_katex-0.9.11.dist-info/top_level.txt
sphinxcontrib_katex-0.9.11.dist-info/RECORD
