Metadata-Version: 2.4
Name: sphinxcontrib-katex
Version: 0.9.11
Summary: A Sphinx extension for rendering math in HTML pages
Author: sphinxcontrib-katex Development Team
License: The MIT License
Project-URL: repository, https://github.com/hagenw/sphinxcontrib-katex/
Project-URL: documentation, https://sphinxcontrib-katex.readthedocs.io
Keywords: sphinx,latex,katex,math,documentation
Classifier: Development Status :: 5 - Production/Stable
Classifier: Intended Audience :: Science/Research
Classifier: Intended Audience :: Developers
Classifier: License :: OSI Approved :: MIT License
Classifier: Operating System :: OS Independent
Classifier: Programming Language :: Python
Classifier: Programming Language :: Python :: 3
Classifier: Programming Language :: Python :: 3.9
Classifier: Programming Language :: Python :: 3.10
Classifier: Programming Language :: Python :: 3.11
Classifier: Programming Language :: Python :: 3.12
Classifier: Programming Language :: Python :: 3.13
Classifier: Topic :: Scientific/Engineering
Classifier: Topic :: Documentation
Classifier: Topic :: Utilities
Requires-Python: >=3.9
License-File: LICENSE
Requires-Dist: sphinx>=1.6
Dynamic: license-file
